rainbow_tqdm/__init__.py
rainbow_tqdm/__main__.py
rainbow_tqdm/rainbow_tqdm.py
rainbow_tqdm-0.1.5.dist-info/LICENSE.txt
rainbow_tqdm-0.1.5.dist-info/METADATA
rainbow_tqdm-0.1.5.dist-info/WHEEL
rainbow_tqdm-0.1.5.dist-info/entry_points.txt
rainbow_tqdm-0.1.5.dist-info/RECORD
