Metadata-Version: 2.1
Name: rainbow_tqdm
Version: 0.1.5
Summary: A rainbow tqdm progress bar with smooth transitions
Home-page: https://github.com/bgorlick/rainbow_tqdm
License: MIT
Author: Benjamin Gorlick
Author-email: ben@aialignment.ai
Requires-Python: >=3.6
Classifier: License :: OSI Approved :: MIT License
Classifier: Programming Language :: Python :: 3
Classifier: Programming Language :: Python :: 3.6
Classifier: Programming Language :: Python :: 3.7
Classifier: Programming Language :: Python :: 3.8
Classifier: Programming Language :: Python :: 3.9
Classifier: Programming Language :: Python :: 3.10
Classifier: Programming Language :: Python :: 3.11
Classifier: Programming Language :: Python :: 3.12
Requires-Dist: tqdm (>=4.22.0)
